LICENSE.md
MANIFEST.in
README.md
setup.py
hxl/__init__.py
hxl/converters.py
hxl/datatypes.py
hxl/filters.py
hxl/geo.py
hxl/hxl-default-schema.json
hxl/input.py
hxl/model.py
hxl/scripts.py
hxl/util.py
hxl/validation.py
hxl/formulas/__init__.py
hxl/formulas/eval.py
hxl/formulas/functions.py
hxl/formulas/lexer.py
hxl/formulas/parser.py
hxl/formulas/parsetab.py
libhxl.egg-info/PKG-INFO
libhxl.egg-info/SOURCES.txt
libhxl.egg-info/dependency_links.txt
libhxl.egg-info/entry_points.txt
libhxl.egg-info/requires.txt
libhxl.egg-info/top_level.txt
tests/test_converters.py
tests/test_datatypes.py
tests/test_filters.py
tests/test_formulas.py
tests/test_geo.py
tests/test_input.py
tests/test_model.py
tests/test_scripts.py
tests/test_validation.py