Metadata-Version: 2.1
Name: libhxl
Version: 5.2.2
Summary: Python support library for the Humanitarian Exchange Language (HXL). See http://hxlstandard.org and https://github.com/HXLStandard/libhxl-python
Home-page: http://hxlproject.org
Author: David Megginson
Author-email: megginson@un.org
Project-URL: Documentation, https://hxlstandard.github.io/libhxl-python/index.html
Project-URL: GitHub, https://github.com/HXLStandard/libhxl-python/
Project-URL: Changelog, https://github.com/HXLStandard/libhxl-python/blob/prod/CHANGELOG
License-File: LICENSE.md
Requires-Dist: jsonpath_ng
Requires-Dist: ply
Requires-Dist: python-dateutil
Requires-Dist: python-io-wrapper>=0.2
Requires-Dist: requests
Requires-Dist: structlog
Requires-Dist: unidecode
Requires-Dist: urllib3
Requires-Dist: wheel
Requires-Dist: xlrd3>=1.1.0
